jojoba_models/__init__.py
jojoba_models/profile.py
jojoba_models/py.typed
jojoba_models-0.1.1.dist-info/WHEEL
jojoba_models-0.1.1.dist-info/METADATA
jojoba_models-0.1.1.dist-info/RECORD
